LICENSE.txt
MANIFEST.in
README.md
build-requirements.txt
pygalle_package.py
requirements.txt
setup.cfg
setup.py
test-requirements.txt
src/pygalle/__init__.py
src/pygalle.core.base.klass.egg-info/PKG-INFO
src/pygalle.core.base.klass.egg-info/SOURCES.txt
src/pygalle.core.base.klass.egg-info/dependency_links.txt
src/pygalle.core.base.klass.egg-info/namespace_packages.txt
src/pygalle.core.base.klass.egg-info/not-zip-safe
src/pygalle.core.base.klass.egg-info/requires.txt
src/pygalle.core.base.klass.egg-info/top_level.txt
src/pygalle/core/__init__.py
src/pygalle/core/base/__init__.py
src/pygalle/core/base/klass/__init__.py
test/test_klass.py