Metadata-Version: 1.2
Name: pygalle.core.base.klass
Version: 0.1.3
Summary: A base class used by the Pygalle framework.
Home-page: http://github.com/pygalle-io/pygalle.core.base.klass
Author: SAS 9 Février
Author-email: contact@9fevrier.com
License: Type license() to see the full license text
Download-URL: https://github.com/pygalle-io/pygalle.core.base.klass/archive/v0.1.3.tar.gz
Keywords: pygalle,pygalle.io,core,base,class,oop,microlibrary
Platform: UNKNOWN
Classifier: Development Status :: 3 - Alpha
Classifier: Topic :: Software Development :: Libraries :: Application Frameworks
Classifier: License :: OSI Approved :: MIT License
Classifier: Programming Language :: Python :: 3.5
Classifier: Programming Language :: Python :: 3.6
Requires-Python: >=3.5, !=3.0.*, !=3.1.*, !=3.2.*, !=3.3.*
